soufi/__init__.py
soufi/_version.py
soufi/cli.py
soufi/exceptions.py
soufi/finder.py
soufi/finders/almalinux.py
soufi/finders/alpine.py
soufi/finders/centos.py
soufi/finders/crate.py
soufi/finders/debian.py
soufi/finders/gem.py
soufi/finders/golang.py
soufi/finders/java.py
soufi/finders/npm.py
soufi/finders/photon.py
soufi/finders/php_composer.py
soufi/finders/php_pecl.py
soufi/finders/python.py
soufi/finders/rhel.py
soufi/finders/ubuntu.py
soufi/finders/yum.py
soufi-2025.9.17.dist-info/METADATA
soufi-2025.9.17.dist-info/WHEEL
soufi-2025.9.17.dist-info/entry_points.txt
soufi-2025.9.17.dist-info/licenses/AUTHORS
soufi-2025.9.17.dist-info/licenses/LICENCE.txt
soufi-2025.9.17.dist-info/RECORD
