Metadata-Version: 2.3
Name: soufi
Version: 2025.9.17
Project-URL: Source, https://github.com/juledwar/soufi
Author-email: Julian Edwards <juledwar@cisco.com>
Maintainer-email: Julian Edwards <juledwar@cisco.com>, Nicolas Simonds <nisimond@cisco.com>
License-Expression: Apache-2.0
License-File: AUTHORS
License-File: LICENCE.txt
Classifier: Development Status :: 5 - Production/Stable
Classifier: Environment :: Console
Classifier: Intended Audience :: Developers
Classifier: Intended Audience :: Information Technology
Classifier: Intended Audience :: System Administrators
Classifier: Natural Language :: English
Classifier: Operating System :: POSIX :: Linux
Classifier: Programming Language :: Python :: 3
Classifier: Programming Language :: Python :: 3.8
Classifier: Programming Language :: Python :: 3.9
Classifier: Programming Language :: Python :: 3.10
Classifier: Programming Language :: Python :: 3.11
Classifier: Topic :: System :: Systems Administration
Classifier: Topic :: Utilities
Requires-Dist: beautifulsoup4
Requires-Dist: cryptography>=3.3.1
Requires-Dist: dogpile-cache>=1.1.5
Requires-Dist: launchpadlib>=1.10.13
Requires-Dist: lxml>=4.6.3
Requires-Dist: repomd>=0.2.1
Requires-Dist: requests-oauthlib>=1.3.0
Requires-Dist: requests>=2.25.1
Provides-Extra: bootstrap
Requires-Dist: hatch; extra == 'bootstrap'
Requires-Dist: hatch-vcs; extra == 'bootstrap'
Requires-Dist: pip; extra == 'bootstrap'
Requires-Dist: uv; extra == 'bootstrap'
Requires-Dist: virtualenv; extra == 'bootstrap'
Requires-Dist: wheel; extra == 'bootstrap'
Provides-Extra: cli
Requires-Dist: click>=7.1.2; extra == 'cli'
Requires-Dist: pylru>=1.2.0; extra == 'cli'
Provides-Extra: test
Requires-Dist: build; extra == 'test'
Requires-Dist: coverage[toml]; extra == 'test'
Requires-Dist: fixtures; extra == 'test'
Requires-Dist: ipython; extra == 'test'
Requires-Dist: pdbpp; extra == 'test'
Requires-Dist: ruff; extra == 'test'
Requires-Dist: stestr; extra == 'test'
Requires-Dist: testresources; extra == 'test'
Requires-Dist: testscenarios; extra == 'test'
Requires-Dist: testtools; extra == 'test'
Requires-Dist: twine; extra == 'test'
